llm/__init__.py
llm/optimized/__init__.py
llm/optimized/inference/__init__.py
llm/optimized/inference/_version.py
llm/optimized/inference/api_server.py
llm/optimized/inference/configs.py
llm/optimized/inference/constants.py
llm/optimized/inference/conversation.py
llm/optimized/inference/error_handler.py
llm/optimized/inference/fm_score.py
llm/optimized/inference/interceptor.py
llm/optimized/inference/logging_config.py
llm/optimized/inference/managed_inference.py
llm/optimized/inference/model_config_factory.py
llm/optimized/inference/model_utils.py
llm/optimized/inference/prompt_formatter.py
llm/optimized/inference/replica_manager.py
llm/optimized/inference/request_adapter.py
llm/optimized/inference/score.py
llm/optimized/inference/utils.py
llm/optimized/inference/vllm_api_server.py
llm/optimized/inference/api_server_setup/__init__.py
llm/optimized/inference/api_server_setup/openapi.json
llm/optimized/inference/api_server_setup/protocol.py
llm/optimized/inference/custom_model_configurations/__init__.py
llm/optimized/inference/custom_model_configurations/base_configuration_builder.py
llm/optimized/inference/custom_model_configurations/diffusion_configuration_builder.py
llm/optimized/inference/custom_model_configurations/schema_output.py
llm/optimized/inference/engine/__init__.py
llm/optimized/inference/engine/_hf_predictors.py
llm/optimized/inference/engine/engine.py
llm/optimized/inference/engine/hf_engine.py
llm/optimized/inference/engine/mii_engine.py
llm/optimized/inference/engine/mii_engine_v2.py
llm/optimized/inference/engine/vllm_engine.py
llm_optimized_inference-0.2.46.dist-info/licenses/LICENSE
llm_optimized_inference-0.2.46.dist-info/METADATA
llm_optimized_inference-0.2.46.dist-info/WHEEL
llm_optimized_inference-0.2.46.dist-info/top_level.txt
llm_optimized_inference-0.2.46.dist-info/RECORD
