Metadata-Version: 2.4
Name: llm-optimized-inference
Version: 0.2.46
Home-page: 
Author: Microsoft
Author-email: 
Classifier: Development Status :: 3 - Alpha
Classifier: Intended Audience :: Developers
Classifier: License :: OSI Approved :: MIT License
Classifier: Programming Language :: Python :: 3.9
Classifier: Programming Language :: Python :: 3.10
Requires-Python: >=3.9
License-File: LICENSE
Requires-Dist: vllm==0.13.0
Requires-Dist: deepspeed==0.15.1
Requires-Dist: deepspeed-kernels==0.0.1.dev1698255861
Requires-Dist: diffusers==0.26.2
Requires-Dist: pandas==2.1.4
Requires-Dist: transformers==4.56.0
Requires-Dist: aiolimiter==1.1.1
Requires-Dist: azure-ai-contentsafety==1.0.0b1
Requires-Dist: azure-ai-ml==1.13.0
Requires-Dist: azureml-inference-server-http==1.5.1
Requires-Dist: azureml-mlflow==1.60.0
Requires-Dist: azureml-ai-monitoring==1.0.0
Requires-Dist: azure-identity==1.23.0
Requires-Dist: requests==2.32.4
Requires-Dist: aiohttp==3.12.14
Requires-Dist: scipy==1.15.3
Requires-Dist: accelerate==1.9.0
Requires-Dist: sacremoses==0.1.1
Requires-Dist: fastapi==0.120.4
Requires-Dist: Jinja2==3.1.6
Requires-Dist: Flask-Cors==6.0.0
Requires-Dist: gunicorn==23.0.0
Requires-Dist: deepspeed-mii==0.3.3
Requires-Dist: soundfile==0.13.1
Requires-Dist: backoff==2.2.1
Requires-Dist: librosa==0.11.0
Requires-Dist: h2==4.3.0
Provides-Extra: dev
Requires-Dist: pytest; extra == "dev"
Dynamic: author
Dynamic: classifier
Dynamic: description
Dynamic: description-content-type
Dynamic: license-file
Dynamic: provides-extra
Dynamic: requires-dist
Dynamic: requires-python
